{"efVersion":"0.11.4","efModuleName":["Data","Lens","Lens"],"efExports":[{"ReExportRef":[["Data","Lens","Types"],{"TypeRef":["ALens",[]]}]},{"ReExportRef":[["Data","Lens","Types"],{"TypeRef":["ALens'",[]]}]},{"ReExportRef":[["Data","Lens","Types"],{"TypeRef":["AnIndexedLens",[]]}]},{"ReExportRef":[["Data","Lens","Types"],{"TypeRef":["AnIndexedLens'",[]]}]},{"ReExportRef":[["Data","Lens","Types"],{"TypeRef":["IndexedLens",[]]}]},{"ReExportRef":[["Data","Lens","Types"],{"TypeRef":["IndexedLens'",[]]}]},{"ReExportRef":[["Data","Lens","Types"],{"TypeRef":["Lens",[]]}]},{"ReExportRef":[["Data","Lens","Types"],{"TypeRef":["Lens'",[]]}]},{"ValueRef":{"Ident":"cloneIndexedLens"}},{"ValueRef":{"Ident":"cloneLens"}},{"ValueRef":{"Ident":"ilens"}},{"ValueRef":{"Ident":"ilens'"}},{"ValueRef":{"Ident":"lens"}},{"ValueRef":{"Ident":"lens'"}},{"ValueRef":{"Ident":"withIndexedLens"}},{"ValueRef":{"Ident":"withLens"}},{"PositionedDeclarationRef":[{"start":[11,5],"name":"bower_components/purescript-profunctor-lenses/src/Data/Lens/Lens.purs","end":[11,27]},[],{"ModuleRef":["Data","Lens","Types"]}]}],"efImports":[{"eiModule":["Prim"],"eiImportType":{"Implicit":[]},"eiImportedAs":null},{"eiModule":["Prelude"],"eiImportType":{"Implicit":[]},"eiImportedAs":null},{"eiModule":["Data","Lens","Internal","Shop"],"eiImportType":{"Explicit":[{"PositionedDeclarationRef":[{"start":[16,33],"name":"bower_components/purescript-profunctor-lenses/src/Data/Lens/Lens.purs","end":[16,41]},[],{"TypeRef":["Shop",null]}]}]},"eiImportedAs":null},{"eiModule":["Data","Lens","Internal","Indexed"],"eiImportType":{"Explicit":[{"PositionedDeclarationRef":[{"start":[17,36],"name":"bower_components/purescript-profunctor-lenses/src/Data/Lens/Lens.purs","end":[17,47]},[],{"TypeRef":["Indexed",null]}]}]},"eiImportedAs":null},{"eiModule":["Data","Lens","Types"],"eiImportType":{"Explicit":[{"PositionedDeclarationRef":[{"start":[19,5],"name":"bower_components/purescript-profunctor-lenses/src/Data/Lens/Lens.purs","end":[19,9]},[],{"TypeRef":["Lens",[]]}]},{"PositionedDeclarationRef":[{"start":[19,12],"name":"bower_components/purescript-profunctor-lenses/src/Data/Lens/Lens.purs","end":[19,17]},[],{"TypeRef":["Lens'",[]]}]},{"PositionedDeclarationRef":[{"start":[19,19],"name":"bower_components/purescript-profunctor-lenses/src/Data/Lens/Lens.purs","end":[19,24]},[],{"TypeRef":["ALens",[]]}]},{"PositionedDeclarationRef":[{"start":[19,26],"name":"bower_components/purescript-profunctor-lenses/src/Data/Lens/Lens.purs","end":[19,32]},[],{"TypeRef":["ALens'",[]]}]},{"PositionedDeclarationRef":[{"start":[20,5],"name":"bower_components/purescript-profunctor-lenses/src/Data/Lens/Lens.purs","end":[20,16]},[],{"TypeRef":["IndexedLens",[]]}]},{"PositionedDeclarationRef":[{"start":[20,18],"name":"bower_components/purescript-profunctor-lenses/src/Data/Lens/Lens.purs","end":[20,30]},[],{"TypeRef":["IndexedLens'",[]]}]},{"PositionedDeclarationRef":[{"start":[20,32],"name":"bower_components/purescript-profunctor-lenses/src/Data/Lens/Lens.purs","end":[20,45]},[],{"TypeRef":["AnIndexedLens",[]]}]},{"PositionedDeclarationRef":[{"start":[20,47],"name":"bower_components/purescript-profunctor-lenses/src/Data/Lens/Lens.purs","end":[20,61]},[],{"TypeRef":["AnIndexedLens'",[]]}]}]},"eiImportedAs":null},{"eiModule":["Data","Profunctor"],"eiImportType":{"Explicit":[{"PositionedDeclarationRef":[{"start":[22,25],"name":"bower_components/purescript-profunctor-lenses/src/Data/Lens/Lens.purs","end":[22,30]},[],{"ValueRef":{"Ident":"dimap"}}]}]},"eiImportedAs":null},{"eiModule":["Data","Profunctor","Strong"],"eiImportType":{"Explicit":[{"PositionedDeclarationRef":[{"start":[23,32],"name":"bower_components/purescript-profunctor-lenses/src/Data/Lens/Lens.purs","end":[23,37]},[],{"ValueRef":{"Ident":"first"}}]}]},"eiImportedAs":null},{"eiModule":["Data","Tuple"],"eiImportType":{"Explicit":[{"PositionedDeclarationRef":[{"start":[24,20],"name":"bower_components/purescript-profunctor-lenses/src/Data/Lens/Lens.purs","end":[24,29]},[],{"TypeRef":["Tuple",null]}]}]},"eiImportedAs":null},{"eiModule":["Data","Newtype"],"eiImportType":{"Explicit":[{"PositionedDeclarationRef":[{"start":[25,21],"name":"bower_components/purescript-profunctor-lenses/src/Data/Lens/Lens.purs","end":[25,23]},[],{"ValueRef":{"Ident":"un"}}]}]},"eiImportedAs":null}],"efFixities":[],"efTypeFixities":[],"efDeclarations":[{"EDValue":{"edValueName":{"Ident":"cloneIndexedLens"},"edValueType":{"tag":"ForAll","contents":["b",{"tag":"ForAll","contents":["a",{"tag":"ForAll","contents":["t",{"tag":"ForAll","contents":["s",{"tag":"ForAll","contents":["i",{"tag":"TypeApp","contents":[{"tag":"TypeApp","contents":[{"tag":"TypeConstructor","contents":[["Prim"],"Function"]},{"tag":"TypeApp","contents":[{"tag":"TypeApp","contents":[{"tag":"TypeConstructor","contents":[["Prim"],"Function"]},{"tag":"TypeApp","contents":[{"tag":"TypeApp","contents":[{"tag":"TypeApp","contents":[{"tag":"TypeApp","contents":[{"tag":"TypeConstructor","contents":[["Data","Lens","Internal","Indexed"],"Indexed"]},{"tag":"TypeApp","contents":[{"tag":"TypeApp","contents":[{"tag":"TypeConstructor","contents":[["Data","Lens","Internal","Shop"],"Shop"]},{"tag":"TypeApp","contents":[{"tag":"TypeApp","contents":[{"tag":"TypeConstructor","contents":[["Data","Tuple"],"Tuple"]},{"tag":"TypeVar","contents":"i"}]},{"tag":"TypeVar","contents":"a"}]}]},{"tag":"TypeVar","contents":"b"}]}]},{"tag":"TypeVar","contents":"i"}]},{"tag":"TypeVar","contents":"a"}]},{"tag":"TypeVar","contents":"b"}]}]},{"tag":"TypeApp","contents":[{"tag":"TypeApp","contents":[{"tag":"TypeApp","contents":[{"tag":"TypeApp","contents":[{"tag":"TypeConstructor","contents":[["Data","Lens","Internal","Shop"],"Shop"]},{"tag":"TypeApp","contents":[{"tag":"TypeApp","contents":[{"tag":"TypeConstructor","contents":[["Data","Tuple"],"Tuple"]},{"tag":"TypeVar","contents":"i"}]},{"tag":"TypeVar","contents":"a"}]}]},{"tag":"TypeVar","contents":"b"}]},{"tag":"TypeVar","contents":"s"}]},{"tag":"TypeVar","contents":"t"}]}]}]},{"tag":"ForAll","contents":["p",{"tag":"ConstrainedType","contents":[{"constraintClass":[["Data","Profunctor","Strong"],"Strong"],"constraintArgs":[{"tag":"TypeVar","contents":"p"}],"constraintData":null},{"tag":"TypeApp","contents":[{"tag":"TypeApp","contents":[{"tag":"TypeConstructor","contents":[["Prim"],"Function"]},{"tag":"TypeApp","contents":[{"tag":"TypeApp","contents":[{"tag":"TypeApp","contents":[{"tag":"TypeApp","contents":[{"tag":"TypeConstructor","contents":[["Data","Lens","Internal","Indexed"],"Indexed"]},{"tag":"TypeVar","contents":"p"}]},{"tag":"TypeVar","contents":"i"}]},{"tag":"TypeVar","contents":"a"}]},{"tag":"TypeVar","contents":"b"}]}]},{"tag":"TypeApp","contents":[{"tag":"TypeApp","contents":[{"tag":"TypeVar","contents":"p"},{"tag":"TypeVar","contents":"s"}]},{"tag":"TypeVar","contents":"t"}]}]}]},80]}]},81]},82]},83]},84]},85]}}},{"EDValue":{"edValueName":{"Ident":"cloneLens"},"edValueType":{"tag":"ForAll","contents":["b",{"tag":"ForAll","contents":["a",{"tag":"ForAll","contents":["t",{"tag":"ForAll","contents":["s",{"tag":"TypeApp","contents":[{"tag":"TypeApp","contents":[{"tag":"TypeConstructor","contents":[["Prim"],"Function"]},{"tag":"TypeApp","contents":[{"tag":"TypeApp","contents":[{"tag":"TypeConstructor","contents":[["Prim"],"Function"]},{"tag":"TypeApp","contents":[{"tag":"TypeApp","contents":[{"tag":"TypeApp","contents":[{"tag":"TypeApp","contents":[{"tag":"TypeConstructor","contents":[["Data","Lens","Internal","Shop"],"Shop"]},{"tag":"TypeVar","contents":"a"}]},{"tag":"TypeVar","contents":"b"}]},{"tag":"TypeVar","contents":"a"}]},{"tag":"TypeVar","contents":"b"}]}]},{"tag":"TypeApp","contents":[{"tag":"TypeApp","contents":[{"tag":"TypeApp","contents":[{"tag":"TypeApp","contents":[{"tag":"TypeConstructor","contents":[["Data","Lens","Internal","Shop"],"Shop"]},{"tag":"TypeVar","contents":"a"}]},{"tag":"TypeVar","contents":"b"}]},{"tag":"TypeVar","contents":"s"}]},{"tag":"TypeVar","contents":"t"}]}]}]},{"tag":"ForAll","contents":["p",{"tag":"ConstrainedType","contents":[{"constraintClass":[["Data","Profunctor","Strong"],"Strong"],"constraintArgs":[{"tag":"TypeVar","contents":"p"}],"constraintData":null},{"tag":"TypeApp","contents":[{"tag":"TypeApp","contents":[{"tag":"TypeConstructor","contents":[["Prim"],"Function"]},{"tag":"TypeApp","contents":[{"tag":"TypeApp","contents":[{"tag":"TypeVar","contents":"p"},{"tag":"TypeVar","contents":"a"}]},{"tag":"TypeVar","contents":"b"}]}]},{"tag":"TypeApp","contents":[{"tag":"TypeApp","contents":[{"tag":"TypeVar","contents":"p"},{"tag":"TypeVar","contents":"s"}]},{"tag":"TypeVar","contents":"t"}]}]}]},70]}]},71]},72]},73]},74]}}},{"EDValue":{"edValueName":{"Ident":"ilens"},"edValueType":{"tag":"ForAll","contents":["b",{"tag":"ForAll","contents":["a",{"tag":"ForAll","contents":["t",{"tag":"ForAll","contents":["s",{"tag":"ForAll","contents":["i",{"tag":"TypeApp","contents":[{"tag":"TypeApp","contents":[{"tag":"TypeConstructor","contents":[["Prim"],"Function"]},{"tag":"TypeApp","contents":[{"tag":"TypeApp","contents":[{"tag":"TypeConstructor","contents":[["Prim"],"Function"]},{"tag":"TypeVar","contents":"s"}]},{"tag":"TypeApp","contents":[{"tag":"TypeApp","contents":[{"tag":"TypeConstructor","contents":[["Data","Tuple"],"Tuple"]},{"tag":"TypeVar","contents":"i"}]},{"tag":"TypeVar","contents":"a"}]}]}]},{"tag":"TypeApp","contents":[{"tag":"TypeApp","contents":[{"tag":"TypeConstructor","contents":[["Prim"],"Function"]},{"tag":"TypeApp","contents":[{"tag":"TypeApp","contents":[{"tag":"TypeConstructor","contents":[["Prim"],"Function"]},{"tag":"TypeVar","contents":"s"}]},{"tag":"TypeApp","contents":[{"tag":"TypeApp","contents":[{"tag":"TypeConstructor","contents":[["Prim"],"Function"]},{"tag":"TypeVar","contents":"b"}]},{"tag":"TypeVar","contents":"t"}]}]}]},{"tag":"ForAll","contents":["p",{"tag":"ConstrainedType","contents":[{"constraintClass":[["Data","Profunctor","Strong"],"Strong"],"constraintArgs":[{"tag":"TypeVar","contents":"p"}],"constraintData":null},{"tag":"TypeApp","contents":[{"tag":"TypeApp","contents":[{"tag":"TypeConstructor","contents":[["Prim"],"Function"]},{"tag":"TypeApp","contents":[{"tag":"TypeApp","contents":[{"tag":"TypeApp","contents":[{"tag":"TypeApp","contents":[{"tag":"TypeConstructor","contents":[["Data","Lens","Internal","Indexed"],"Indexed"]},{"tag":"TypeVar","contents":"p"}]},{"tag":"TypeVar","contents":"i"}]},{"tag":"TypeVar","contents":"a"}]},{"tag":"TypeVar","contents":"b"}]}]},{"tag":"TypeApp","contents":[{"tag":"TypeApp","contents":[{"tag":"TypeVar","contents":"p"},{"tag":"TypeVar","contents":"s"}]},{"tag":"TypeVar","contents":"t"}]}]}]},58]}]}]},59]},60]},61]},62]},63]}}},{"EDValue":{"edValueName":{"Ident":"ilens'"},"edValueType":{"tag":"ForAll","contents":["b",{"tag":"ForAll","contents":["a",{"tag":"ForAll","contents":["t",{"tag":"ForAll","contents":["s",{"tag":"ForAll","contents":["i",{"tag":"TypeApp","contents":[{"tag":"TypeApp","contents":[{"tag":"TypeConstructor","contents":[["Prim"],"Function"]},{"tag":"TypeApp","contents":[{"tag":"TypeApp","contents":[{"tag":"TypeConstructor","contents":[["Prim"],"Function"]},{"tag":"TypeVar","contents":"s"}]},{"tag":"TypeApp","contents":[{"tag":"TypeApp","contents":[{"tag":"TypeConstructor","contents":[["Data","Tuple"],"Tuple"]},{"tag":"TypeApp","contents":[{"tag":"TypeApp","contents":[{"tag":"TypeConstructor","contents":[["Data","Tuple"],"Tuple"]},{"tag":"TypeVar","contents":"i"}]},{"tag":"TypeVar","contents":"a"}]}]},{"tag":"TypeApp","contents":[{"tag":"TypeApp","contents":[{"tag":"TypeConstructor","contents":[["Prim"],"Function"]},{"tag":"TypeVar","contents":"b"}]},{"tag":"TypeVar","contents":"t"}]}]}]}]},{"tag":"ForAll","contents":["p",{"tag":"ConstrainedType","contents":[{"constraintClass":[["Data","Profunctor","Strong"],"Strong"],"constraintArgs":[{"tag":"TypeVar","contents":"p"}],"constraintData":null},{"tag":"TypeApp","contents":[{"tag":"TypeApp","contents":[{"tag":"TypeConstructor","contents":[["Prim"],"Function"]},{"tag":"TypeApp","contents":[{"tag":"TypeApp","contents":[{"tag":"TypeApp","contents":[{"tag":"TypeApp","contents":[{"tag":"TypeConstructor","contents":[["Data","Lens","Internal","Indexed"],"Indexed"]},{"tag":"TypeVar","contents":"p"}]},{"tag":"TypeVar","contents":"i"}]},{"tag":"TypeVar","contents":"a"}]},{"tag":"TypeVar","contents":"b"}]}]},{"tag":"TypeApp","contents":[{"tag":"TypeApp","contents":[{"tag":"TypeVar","contents":"p"},{"tag":"TypeVar","contents":"s"}]},{"tag":"TypeVar","contents":"t"}]}]}]},42]}]},43]},44]},45]},46]},47]}}},{"EDValue":{"edValueName":{"Ident":"lens"},"edValueType":{"tag":"ForAll","contents":["b",{"tag":"ForAll","contents":["a",{"tag":"ForAll","contents":["t",{"tag":"ForAll","contents":["s",{"tag":"TypeApp","contents":[{"tag":"TypeApp","contents":[{"tag":"TypeConstructor","contents":[["Prim"],"Function"]},{"tag":"TypeApp","contents":[{"tag":"TypeApp","contents":[{"tag":"TypeConstructor","contents":[["Prim"],"Function"]},{"tag":"TypeVar","contents":"s"}]},{"tag":"TypeVar","contents":"a"}]}]},{"tag":"TypeApp","contents":[{"tag":"TypeApp","contents":[{"tag":"TypeConstructor","contents":[["Prim"],"Function"]},{"tag":"TypeApp","contents":[{"tag":"TypeApp","contents":[{"tag":"TypeConstructor","contents":[["Prim"],"Function"]},{"tag":"TypeVar","contents":"s"}]},{"tag":"TypeApp","contents":[{"tag":"TypeApp","contents":[{"tag":"TypeConstructor","contents":[["Prim"],"Function"]},{"tag":"TypeVar","contents":"b"}]},{"tag":"TypeVar","contents":"t"}]}]}]},{"tag":"ForAll","contents":["p",{"tag":"ConstrainedType","contents":[{"constraintClass":[["Data","Profunctor","Strong"],"Strong"],"constraintArgs":[{"tag":"TypeVar","contents":"p"}],"constraintData":null},{"tag":"TypeApp","contents":[{"tag":"TypeApp","contents":[{"tag":"TypeConstructor","contents":[["Prim"],"Function"]},{"tag":"TypeApp","contents":[{"tag":"TypeApp","contents":[{"tag":"TypeVar","contents":"p"},{"tag":"TypeVar","contents":"a"}]},{"tag":"TypeVar","contents":"b"}]}]},{"tag":"TypeApp","contents":[{"tag":"TypeApp","contents":[{"tag":"TypeVar","contents":"p"},{"tag":"TypeVar","contents":"s"}]},{"tag":"TypeVar","contents":"t"}]}]}]},32]}]}]},33]},34]},35]},36]}}},{"EDValue":{"edValueName":{"Ident":"lens'"},"edValueType":{"tag":"ForAll","contents":["b",{"tag":"ForAll","contents":["a",{"tag":"ForAll","contents":["t",{"tag":"ForAll","contents":["s",{"tag":"TypeApp","contents":[{"tag":"TypeApp","contents":[{"tag":"TypeConstructor","contents":[["Prim"],"Function"]},{"tag":"TypeApp","contents":[{"tag":"TypeApp","contents":[{"tag":"TypeConstructor","contents":[["Prim"],"Function"]},{"tag":"TypeVar","contents":"s"}]},{"tag":"TypeApp","contents":[{"tag":"TypeApp","contents":[{"tag":"TypeConstructor","contents":[["Data","Tuple"],"Tuple"]},{"tag":"TypeVar","contents":"a"}]},{"tag":"TypeApp","contents":[{"tag":"TypeApp","contents":[{"tag":"TypeConstructor","contents":[["Prim"],"Function"]},{"tag":"TypeVar","contents":"b"}]},{"tag":"TypeVar","contents":"t"}]}]}]}]},{"tag":"ForAll","contents":["p",{"tag":"ConstrainedType","contents":[{"constraintClass":[["Data","Profunctor","Strong"],"Strong"],"constraintArgs":[{"tag":"TypeVar","contents":"p"}],"constraintData":null},{"tag":"TypeApp","contents":[{"tag":"TypeApp","contents":[{"tag":"TypeConstructor","contents":[["Prim"],"Function"]},{"tag":"TypeApp","contents":[{"tag":"TypeApp","contents":[{"tag":"TypeVar","contents":"p"},{"tag":"TypeVar","contents":"a"}]},{"tag":"TypeVar","contents":"b"}]}]},{"tag":"TypeApp","contents":[{"tag":"TypeApp","contents":[{"tag":"TypeVar","contents":"p"},{"tag":"TypeVar","contents":"s"}]},{"tag":"TypeVar","contents":"t"}]}]}]},22]}]},23]},24]},25]},26]}}},{"EDValue":{"edValueName":{"Ident":"withIndexedLens"},"edValueType":{"tag":"ForAll","contents":["r",{"tag":"ForAll","contents":["b",{"tag":"ForAll","contents":["a",{"tag":"ForAll","contents":["t",{"tag":"ForAll","contents":["s",{"tag":"ForAll","contents":["i",{"tag":"TypeApp","contents":[{"tag":"TypeApp","contents":[{"tag":"TypeConstructor","contents":[["Prim"],"Function"]},{"tag":"TypeApp","contents":[{"tag":"TypeApp","contents":[{"tag":"TypeConstructor","contents":[["Prim"],"Function"]},{"tag":"TypeApp","contents":[{"tag":"TypeApp","contents":[{"tag":"TypeApp","contents":[{"tag":"TypeApp","contents":[{"tag":"TypeConstructor","contents":[["Data","Lens","Internal","Indexed"],"Indexed"]},{"tag":"TypeApp","contents":[{"tag":"TypeApp","contents":[{"tag":"TypeConstructor","contents":[["Data","Lens","Internal","Shop"],"Shop"]},{"tag":"TypeApp","contents":[{"tag":"TypeApp","contents":[{"tag":"TypeConstructor","contents":[["Data","Tuple"],"Tuple"]},{"tag":"TypeVar","contents":"i"}]},{"tag":"TypeVar","contents":"a"}]}]},{"tag":"TypeVar","contents":"b"}]}]},{"tag":"TypeVar","contents":"i"}]},{"tag":"TypeVar","contents":"a"}]},{"tag":"TypeVar","contents":"b"}]}]},{"tag":"TypeApp","contents":[{"tag":"TypeApp","contents":[{"tag":"TypeApp","contents":[{"tag":"TypeApp","contents":[{"tag":"TypeConstructor","contents":[["Data","Lens","Internal","Shop"],"Shop"]},{"tag":"TypeApp","contents":[{"tag":"TypeApp","contents":[{"tag":"TypeConstructor","contents":[["Data","Tuple"],"Tuple"]},{"tag":"TypeVar","contents":"i"}]},{"tag":"TypeVar","contents":"a"}]}]},{"tag":"TypeVar","contents":"b"}]},{"tag":"TypeVar","contents":"s"}]},{"tag":"TypeVar","contents":"t"}]}]}]},{"tag":"TypeApp","contents":[{"tag":"TypeApp","contents":[{"tag":"TypeConstructor","contents":[["Prim"],"Function"]},{"tag":"TypeApp","contents":[{"tag":"TypeApp","contents":[{"tag":"TypeConstructor","contents":[["Prim"],"Function"]},{"tag":"TypeApp","contents":[{"tag":"TypeApp","contents":[{"tag":"TypeConstructor","contents":[["Prim"],"Function"]},{"tag":"TypeVar","contents":"s"}]},{"tag":"TypeApp","contents":[{"tag":"TypeApp","contents":[{"tag":"TypeConstructor","contents":[["Data","Tuple"],"Tuple"]},{"tag":"TypeVar","contents":"i"}]},{"tag":"TypeVar","contents":"a"}]}]}]},{"tag":"TypeApp","contents":[{"tag":"TypeApp","contents":[{"tag":"TypeConstructor","contents":[["Prim"],"Function"]},{"tag":"TypeApp","contents":[{"tag":"TypeApp","contents":[{"tag":"TypeConstructor","contents":[["Prim"],"Function"]},{"tag":"TypeVar","contents":"s"}]},{"tag":"TypeApp","contents":[{"tag":"TypeApp","contents":[{"tag":"TypeConstructor","contents":[["Prim"],"Function"]},{"tag":"TypeVar","contents":"b"}]},{"tag":"TypeVar","contents":"t"}]}]}]},{"tag":"TypeVar","contents":"r"}]}]}]},{"tag":"TypeVar","contents":"r"}]}]},10]},11]},12]},13]},14]},15]}}},{"EDValue":{"edValueName":{"Ident":"withLens"},"edValueType":{"tag":"ForAll","contents":["r",{"tag":"ForAll","contents":["b",{"tag":"ForAll","contents":["a",{"tag":"ForAll","contents":["t",{"tag":"ForAll","contents":["s",{"tag":"TypeApp","contents":[{"tag":"TypeApp","contents":[{"tag":"TypeConstructor","contents":[["Prim"],"Function"]},{"tag":"TypeApp","contents":[{"tag":"TypeApp","contents":[{"tag":"TypeConstructor","contents":[["Prim"],"Function"]},{"tag":"TypeApp","contents":[{"tag":"TypeApp","contents":[{"tag":"TypeApp","contents":[{"tag":"TypeApp","contents":[{"tag":"TypeConstructor","contents":[["Data","Lens","Internal","Shop"],"Shop"]},{"tag":"TypeVar","contents":"a"}]},{"tag":"TypeVar","contents":"b"}]},{"tag":"TypeVar","contents":"a"}]},{"tag":"TypeVar","contents":"b"}]}]},{"tag":"TypeApp","contents":[{"tag":"TypeApp","contents":[{"tag":"TypeApp","contents":[{"tag":"TypeApp","contents":[{"tag":"TypeConstructor","contents":[["Data","Lens","Internal","Shop"],"Shop"]},{"tag":"TypeVar","contents":"a"}]},{"tag":"TypeVar","contents":"b"}]},{"tag":"TypeVar","contents":"s"}]},{"tag":"TypeVar","contents":"t"}]}]}]},{"tag":"TypeApp","contents":[{"tag":"TypeApp","contents":[{"tag":"TypeConstructor","contents":[["Prim"],"Function"]},{"tag":"TypeApp","contents":[{"tag":"TypeApp","contents":[{"tag":"TypeConstructor","contents":[["Prim"],"Function"]},{"tag":"TypeApp","contents":[{"tag":"TypeApp","contents":[{"tag":"TypeConstructor","contents":[["Prim"],"Function"]},{"tag":"TypeVar","contents":"s"}]},{"tag":"TypeVar","contents":"a"}]}]},{"tag":"TypeApp","contents":[{"tag":"TypeApp","contents":[{"tag":"TypeConstructor","contents":[["Prim"],"Function"]},{"tag":"TypeApp","contents":[{"tag":"TypeApp","contents":[{"tag":"TypeConstructor","contents":[["Prim"],"Function"]},{"tag":"TypeVar","contents":"s"}]},{"tag":"TypeApp","contents":[{"tag":"TypeApp","contents":[{"tag":"TypeConstructor","contents":[["Prim"],"Function"]},{"tag":"TypeVar","contents":"b"}]},{"tag":"TypeVar","contents":"t"}]}]}]},{"tag":"TypeVar","contents":"r"}]}]}]},{"tag":"TypeVar","contents":"r"}]}]},0]},1]},2]},3]},4]}}}],"efSourceSpan":{"start":[1,1],"name":"bower_components/purescript-profunctor-lenses/src/Data/Lens/Lens.purs","end":[55,60]}}