{"efVersion":"0.11.4","efModuleName":["Control","Monad","Cont","Trans"],"efExports":[{"TypeRef":["ContT",["ContT"]]},{"ReExportRef":[["Control","Monad","Cont","Class"],{"TypeClassRef":"MonadCont"}]},{"ReExportRef":[["Control","Monad","Trans","Class"],{"TypeClassRef":"MonadTrans"}]},{"ReExportRef":[["Control","Monad","Cont","Class"],{"ValueRef":{"Ident":"callCC"}}]},{"ReExportRef":[["Control","Monad","Trans","Class"],{"ValueRef":{"Ident":"lift"}}]},{"ValueRef":{"Ident":"mapContT"}},{"ValueRef":{"Ident":"runContT"}},{"ValueRef":{"Ident":"withContT"}},{"PositionedDeclarationRef":[{"start":[5,5],"name":"bower_components/purescript-transformers/src/Control/Monad/Cont/Trans.purs","end":[5,37]},[],{"ModuleRef":["Control","Monad","Trans","Class"]}]},{"PositionedDeclarationRef":[{"start":[6,5],"name":"bower_components/purescript-transformers/src/Control/Monad/Cont/Trans.purs","end":[6,36]},[],{"ModuleRef":["Control","Monad","Cont","Class"]}]},{"TypeInstanceRef":{"Ident":"newtypeContT"}},{"TypeInstanceRef":{"Ident":"monadContContT"}},{"TypeInstanceRef":{"Ident":"functorContT"}},{"TypeInstanceRef":{"Ident":"applyContT"}},{"TypeInstanceRef":{"Ident":"applicativeContT"}},{"TypeInstanceRef":{"Ident":"bindContT"}},{"TypeInstanceRef":{"Ident":"monadContT"}},{"TypeInstanceRef":{"Ident":"monadTransContT"}},{"TypeInstanceRef":{"Ident":"monadEffContT"}},{"TypeInstanceRef":{"Ident":"monadAskContT"}},{"TypeInstanceRef":{"Ident":"monadReaderContT"}},{"TypeInstanceRef":{"Ident":"monadStateContT"}}],"efImports":[{"eiModule":["Prim"],"eiImportType":{"Implicit":[]},"eiImportedAs":null},{"eiModule":["Prelude"],"eiImportType":{"Implicit":[]},"eiImportedAs":null},{"eiModule":["Control","Monad","Cont","Class"],"eiImportType":{"Explicit":[{"PositionedDeclarationRef":[{"start":[11,34],"name":"bower_components/purescript-transformers/src/Control/Monad/Cont/Trans.purs","end":[11,49]},[],{"TypeClassRef":"MonadCont"}]},{"PositionedDeclarationRef":[{"start":[11,51],"name":"bower_components/purescript-transformers/src/Control/Monad/Cont/Trans.purs","end":[11,57]},[],{"ValueRef":{"Ident":"callCC"}}]}]},"eiImportedAs":null},{"eiModule":["Control","Monad","Eff","Class"],"eiImportType":{"Explicit":[{"PositionedDeclarationRef":[{"start":[12,33],"name":"bower_components/purescript-transformers/src/Control/Monad/Cont/Trans.purs","end":[12,47]},[],{"TypeClassRef":"MonadEff"}]},{"PositionedDeclarationRef":[{"start":[12,49],"name":"bower_components/purescript-transformers/src/Control/Monad/Cont/Trans.purs","end":[12,56]},[],{"ValueRef":{"Ident":"liftEff"}}]}]},"eiImportedAs":null},{"eiModule":["Control","Monad","Reader","Class"],"eiImportType":{"Explicit":[{"PositionedDeclarationRef":[{"start":[13,36],"name":"bower_components/purescript-transformers/src/Control/Monad/Cont/Trans.purs","end":[13,50]},[],{"TypeClassRef":"MonadAsk"}]},{"PositionedDeclarationRef":[{"start":[13,52],"name":"bower_components/purescript-transformers/src/Control/Monad/Cont/Trans.purs","end":[13,69]},[],{"TypeClassRef":"MonadReader"}]},{"PositionedDeclarationRef":[{"start":[13,71],"name":"bower_components/purescript-transformers/src/Control/Monad/Cont/Trans.purs","end":[13,74]},[],{"ValueRef":{"Ident":"ask"}}]},{"PositionedDeclarationRef":[{"start":[13,76],"name":"bower_components/purescript-transformers/src/Control/Monad/Cont/Trans.purs","end":[13,81]},[],{"ValueRef":{"Ident":"local"}}]}]},"eiImportedAs":null},{"eiModule":["Control","Monad","State","Class"],"eiImportType":{"Explicit":[{"PositionedDeclarationRef":[{"start":[14,35],"name":"bower_components/purescript-transformers/src/Control/Monad/Cont/Trans.purs","end":[14,51]},[],{"TypeClassRef":"MonadState"}]},{"PositionedDeclarationRef":[{"start":[14,53],"name":"bower_components/purescript-transformers/src/Control/Monad/Cont/Trans.purs","end":[14,58]},[],{"ValueRef":{"Ident":"state"}}]}]},"eiImportedAs":null},{"eiModule":["Control","Monad","Trans","Class"],"eiImportType":{"Explicit":[{"PositionedDeclarationRef":[{"start":[15,35],"name":"bower_components/purescript-transformers/src/Control/Monad/Cont/Trans.purs","end":[15,51]},[],{"TypeClassRef":"MonadTrans"}]},{"PositionedDeclarationRef":[{"start":[15,53],"name":"bower_components/purescript-transformers/src/Control/Monad/Cont/Trans.purs","end":[15,57]},[],{"ValueRef":{"Ident":"lift"}}]}]},"eiImportedAs":null},{"eiModule":["Data","Newtype"],"eiImportType":{"Explicit":[{"PositionedDeclarationRef":[{"start":[17,22],"name":"bower_components/purescript-transformers/src/Control/Monad/Cont/Trans.purs","end":[17,35]},[],{"TypeClassRef":"Newtype"}]}]},"eiImportedAs":null}],"efFixities":[],"efTypeFixities":[],"efDeclarations":[{"EDType":{"edTypeName":"ContT","edTypeKind":{"tag":"FunKind","contents":[{"tag":"NamedKind","contents":[["Prim"],"Type"]},{"tag":"FunKind","contents":[{"tag":"FunKind","contents":[{"tag":"NamedKind","contents":[["Prim"],"Type"]},{"tag":"NamedKind","contents":[["Prim"],"Type"]}]},{"tag":"FunKind","contents":[{"tag":"NamedKind","contents":[["Prim"],"Type"]},{"tag":"NamedKind","contents":[["Prim"],"Type"]}]}]}]},"edTypeDeclarationKind":{"DataType":{"args":[["r",{"tag":"NamedKind","contents":[["Prim"],"Type"]}],["m",{"tag":"FunKind","contents":[{"tag":"NamedKind","contents":[["Prim"],"Type"]},{"tag":"NamedKind","contents":[["Prim"],"Type"]}]}],["a",{"tag":"NamedKind","contents":[["Prim"],"Type"]}]],"ctors":[["ContT",[{"tag":"TypeApp","contents":[{"tag":"TypeApp","contents":[{"tag":"TypeConstructor","contents":[["Prim"],"Function"]},{"tag":"TypeApp","contents":[{"tag":"TypeApp","contents":[{"tag":"TypeConstructor","contents":[["Prim"],"Function"]},{"tag":"TypeVar","contents":"a"}]},{"tag":"TypeApp","contents":[{"tag":"TypeVar","contents":"m"},{"tag":"TypeVar","contents":"r"}]}]}]},{"tag":"TypeApp","contents":[{"tag":"TypeVar","contents":"m"},{"tag":"TypeVar","contents":"r"}]}]}]]]}}}},{"EDDataConstructor":{"edDataCtorName":"ContT","edDataCtorOrigin":"newtype","edDataCtorTypeCtor":"ContT","edDataCtorType":{"tag":"ForAll","contents":["a",{"tag":"ForAll","contents":["m",{"tag":"ForAll","contents":["r",{"tag":"TypeApp","contents":[{"tag":"TypeApp","contents":[{"tag":"TypeConstructor","contents":[["Prim"],"Function"]},{"tag":"TypeApp","contents":[{"tag":"TypeApp","contents":[{"tag":"TypeConstructor","contents":[["Prim"],"Function"]},{"tag":"TypeApp","contents":[{"tag":"TypeApp","contents":[{"tag":"TypeConstructor","contents":[["Prim"],"Function"]},{"tag":"TypeVar","contents":"a"}]},{"tag":"TypeApp","contents":[{"tag":"TypeVar","contents":"m"},{"tag":"TypeVar","contents":"r"}]}]}]},{"tag":"TypeApp","contents":[{"tag":"TypeVar","contents":"m"},{"tag":"TypeVar","contents":"r"}]}]}]},{"tag":"TypeApp","contents":[{"tag":"TypeApp","contents":[{"tag":"TypeApp","contents":[{"tag":"TypeConstructor","contents":[["Control","Monad","Cont","Trans"],"ContT"]},{"tag":"TypeVar","contents":"r"}]},{"tag":"TypeVar","contents":"m"}]},{"tag":"TypeVar","contents":"a"}]}]},null]},null]},null]},"edDataCtorFields":[{"Ident":"value0"}]}},{"EDValue":{"edValueName":{"Ident":"mapContT"},"edValueType":{"tag":"ForAll","contents":["a",{"tag":"ForAll","contents":["m",{"tag":"ForAll","contents":["r",{"tag":"TypeApp","contents":[{"tag":"TypeApp","contents":[{"tag":"TypeConstructor","contents":[["Prim"],"Function"]},{"tag":"TypeApp","contents":[{"tag":"TypeApp","contents":[{"tag":"TypeConstructor","contents":[["Prim"],"Function"]},{"tag":"TypeApp","contents":[{"tag":"TypeVar","contents":"m"},{"tag":"TypeVar","contents":"r"}]}]},{"tag":"TypeApp","contents":[{"tag":"TypeVar","contents":"m"},{"tag":"TypeVar","contents":"r"}]}]}]},{"tag":"TypeApp","contents":[{"tag":"TypeApp","contents":[{"tag":"TypeConstructor","contents":[["Prim"],"Function"]},{"tag":"TypeApp","contents":[{"tag":"TypeApp","contents":[{"tag":"TypeApp","contents":[{"tag":"TypeConstructor","contents":[["Control","Monad","Cont","Trans"],"ContT"]},{"tag":"TypeVar","contents":"r"}]},{"tag":"TypeVar","contents":"m"}]},{"tag":"TypeVar","contents":"a"}]}]},{"tag":"TypeApp","contents":[{"tag":"TypeApp","contents":[{"tag":"TypeApp","contents":[{"tag":"TypeConstructor","contents":[["Control","Monad","Cont","Trans"],"ContT"]},{"tag":"TypeVar","contents":"r"}]},{"tag":"TypeVar","contents":"m"}]},{"tag":"TypeVar","contents":"a"}]}]}]},137]},138]},139]}}},{"EDValue":{"edValueName":{"Ident":"runContT"},"edValueType":{"tag":"ForAll","contents":["a",{"tag":"ForAll","contents":["m",{"tag":"ForAll","contents":["r",{"tag":"TypeApp","contents":[{"tag":"TypeApp","contents":[{"tag":"TypeConstructor","contents":[["Prim"],"Function"]},{"tag":"TypeApp","contents":[{"tag":"TypeApp","contents":[{"tag":"TypeApp","contents":[{"tag":"TypeConstructor","contents":[["Control","Monad","Cont","Trans"],"ContT"]},{"tag":"TypeVar","contents":"r"}]},{"tag":"TypeVar","contents":"m"}]},{"tag":"TypeVar","contents":"a"}]}]},{"tag":"TypeApp","contents":[{"tag":"TypeApp","contents":[{"tag":"TypeConstructor","contents":[["Prim"],"Function"]},{"tag":"TypeApp","contents":[{"tag":"TypeApp","contents":[{"tag":"TypeConstructor","contents":[["Prim"],"Function"]},{"tag":"TypeVar","contents":"a"}]},{"tag":"TypeApp","contents":[{"tag":"TypeVar","contents":"m"},{"tag":"TypeVar","contents":"r"}]}]}]},{"tag":"TypeApp","contents":[{"tag":"TypeVar","contents":"m"},{"tag":"TypeVar","contents":"r"}]}]}]},8]},9]},10]}}},{"EDValue":{"edValueName":{"Ident":"withContT"},"edValueType":{"tag":"ForAll","contents":["b",{"tag":"ForAll","contents":["a",{"tag":"ForAll","contents":["m",{"tag":"ForAll","contents":["r",{"tag":"TypeApp","contents":[{"tag":"TypeApp","contents":[{"tag":"TypeConstructor","contents":[["Prim"],"Function"]},{"tag":"TypeApp","contents":[{"tag":"TypeApp","contents":[{"tag":"TypeConstructor","contents":[["Prim"],"Function"]},{"tag":"TypeApp","contents":[{"tag":"TypeApp","contents":[{"tag":"TypeConstructor","contents":[["Prim"],"Function"]},{"tag":"TypeVar","contents":"b"}]},{"tag":"TypeApp","contents":[{"tag":"TypeVar","contents":"m"},{"tag":"TypeVar","contents":"r"}]}]}]},{"tag":"TypeApp","contents":[{"tag":"TypeApp","contents":[{"tag":"TypeConstructor","contents":[["Prim"],"Function"]},{"tag":"TypeVar","contents":"a"}]},{"tag":"TypeApp","contents":[{"tag":"TypeVar","contents":"m"},{"tag":"TypeVar","contents":"r"}]}]}]}]},{"tag":"TypeApp","contents":[{"tag":"TypeApp","contents":[{"tag":"TypeConstructor","contents":[["Prim"],"Function"]},{"tag":"TypeApp","contents":[{"tag":"TypeApp","contents":[{"tag":"TypeApp","contents":[{"tag":"TypeConstructor","contents":[["Control","Monad","Cont","Trans"],"ContT"]},{"tag":"TypeVar","contents":"r"}]},{"tag":"TypeVar","contents":"m"}]},{"tag":"TypeVar","contents":"a"}]}]},{"tag":"TypeApp","contents":[{"tag":"TypeApp","contents":[{"tag":"TypeApp","contents":[{"tag":"TypeConstructor","contents":[["Control","Monad","Cont","Trans"],"ContT"]},{"tag":"TypeVar","contents":"r"}]},{"tag":"TypeVar","contents":"m"}]},{"tag":"TypeVar","contents":"b"}]}]}]},0]},1]},2]},3]}}},{"EDInstance":{"edInstanceClassName":[["Data","Newtype"],"Newtype"],"edInstanceName":{"Ident":"newtypeContT"},"edInstanceTypes":[{"tag":"TypeApp","contents":[{"tag":"TypeApp","contents":[{"tag":"TypeApp","contents":[{"tag":"TypeConstructor","contents":[["Control","Monad","Cont","Trans"],"ContT"]},{"tag":"TypeVar","contents":"r"}]},{"tag":"TypeVar","contents":"m"}]},{"tag":"TypeVar","contents":"a"}]},{"tag":"TypeApp","contents":[{"tag":"TypeApp","contents":[{"tag":"TypeConstructor","contents":[["Prim"],"Function"]},{"tag":"TypeApp","contents":[{"tag":"TypeApp","contents":[{"tag":"TypeConstructor","contents":[["Prim"],"Function"]},{"tag":"TypeVar","contents":"a"}]},{"tag":"TypeApp","contents":[{"tag":"TypeVar","contents":"m"},{"tag":"TypeVar","contents":"r"}]}]}]},{"tag":"TypeApp","contents":[{"tag":"TypeVar","contents":"m"},{"tag":"TypeVar","contents":"r"}]}]}],"edInstanceConstraints":[]}},{"EDInstance":{"edInstanceClassName":[["Control","Monad","Cont","Class"],"MonadCont"],"edInstanceName":{"Ident":"monadContContT"},"edInstanceTypes":[{"tag":"TypeApp","contents":[{"tag":"TypeApp","contents":[{"tag":"TypeConstructor","contents":[["Control","Monad","Cont","Trans"],"ContT"]},{"tag":"TypeVar","contents":"r"}]},{"tag":"TypeVar","contents":"m"}]}],"edInstanceConstraints":[{"constraintClass":[["Control","Monad"],"Monad"],"constraintArgs":[{"tag":"TypeVar","contents":"m"}],"constraintData":null}]}},{"EDInstance":{"edInstanceClassName":[["Data","Functor"],"Functor"],"edInstanceName":{"Ident":"functorContT"},"edInstanceTypes":[{"tag":"TypeApp","contents":[{"tag":"TypeApp","contents":[{"tag":"TypeConstructor","contents":[["Control","Monad","Cont","Trans"],"ContT"]},{"tag":"TypeVar","contents":"r"}]},{"tag":"TypeVar","contents":"m"}]}],"edInstanceConstraints":[{"constraintClass":[["Data","Functor"],"Functor"],"constraintArgs":[{"tag":"TypeVar","contents":"m"}],"constraintData":null}]}},{"EDInstance":{"edInstanceClassName":[["Control","Apply"],"Apply"],"edInstanceName":{"Ident":"applyContT"},"edInstanceTypes":[{"tag":"TypeApp","contents":[{"tag":"TypeApp","contents":[{"tag":"TypeConstructor","contents":[["Control","Monad","Cont","Trans"],"ContT"]},{"tag":"TypeVar","contents":"r"}]},{"tag":"TypeVar","contents":"m"}]}],"edInstanceConstraints":[{"constraintClass":[["Control","Apply"],"Apply"],"constraintArgs":[{"tag":"TypeVar","contents":"m"}],"constraintData":null}]}},{"EDInstance":{"edInstanceClassName":[["Control","Applicative"],"Applicative"],"edInstanceName":{"Ident":"applicativeContT"},"edInstanceTypes":[{"tag":"TypeApp","contents":[{"tag":"TypeApp","contents":[{"tag":"TypeConstructor","contents":[["Control","Monad","Cont","Trans"],"ContT"]},{"tag":"TypeVar","contents":"r"}]},{"tag":"TypeVar","contents":"m"}]}],"edInstanceConstraints":[{"constraintClass":[["Control","Applicative"],"Applicative"],"constraintArgs":[{"tag":"TypeVar","contents":"m"}],"constraintData":null}]}},{"EDInstance":{"edInstanceClassName":[["Control","Bind"],"Bind"],"edInstanceName":{"Ident":"bindContT"},"edInstanceTypes":[{"tag":"TypeApp","contents":[{"tag":"TypeApp","contents":[{"tag":"TypeConstructor","contents":[["Control","Monad","Cont","Trans"],"ContT"]},{"tag":"TypeVar","contents":"r"}]},{"tag":"TypeVar","contents":"m"}]}],"edInstanceConstraints":[{"constraintClass":[["Control","Bind"],"Bind"],"constraintArgs":[{"tag":"TypeVar","contents":"m"}],"constraintData":null}]}},{"EDInstance":{"edInstanceClassName":[["Control","Monad"],"Monad"],"edInstanceName":{"Ident":"monadContT"},"edInstanceTypes":[{"tag":"TypeApp","contents":[{"tag":"TypeApp","contents":[{"tag":"TypeConstructor","contents":[["Control","Monad","Cont","Trans"],"ContT"]},{"tag":"TypeVar","contents":"r"}]},{"tag":"TypeVar","contents":"m"}]}],"edInstanceConstraints":[{"constraintClass":[["Control","Monad"],"Monad"],"constraintArgs":[{"tag":"TypeVar","contents":"m"}],"constraintData":null}]}},{"EDInstance":{"edInstanceClassName":[["Control","Monad","Trans","Class"],"MonadTrans"],"edInstanceName":{"Ident":"monadTransContT"},"edInstanceTypes":[{"tag":"TypeApp","contents":[{"tag":"TypeConstructor","contents":[["Control","Monad","Cont","Trans"],"ContT"]},{"tag":"TypeVar","contents":"r"}]}],"edInstanceConstraints":[]}},{"EDInstance":{"edInstanceClassName":[["Control","Monad","Eff","Class"],"MonadEff"],"edInstanceName":{"Ident":"monadEffContT"},"edInstanceTypes":[{"tag":"TypeVar","contents":"eff"},{"tag":"TypeApp","contents":[{"tag":"TypeApp","contents":[{"tag":"TypeConstructor","contents":[["Control","Monad","Cont","Trans"],"ContT"]},{"tag":"TypeVar","contents":"r"}]},{"tag":"TypeVar","contents":"m"}]}],"edInstanceConstraints":[{"constraintClass":[["Control","Monad","Eff","Class"],"MonadEff"],"constraintArgs":[{"tag":"TypeVar","contents":"eff"},{"tag":"TypeVar","contents":"m"}],"constraintData":null}]}},{"EDInstance":{"edInstanceClassName":[["Control","Monad","Reader","Class"],"MonadAsk"],"edInstanceName":{"Ident":"monadAskContT"},"edInstanceTypes":[{"tag":"TypeVar","contents":"r1"},{"tag":"TypeApp","contents":[{"tag":"TypeApp","contents":[{"tag":"TypeConstructor","contents":[["Control","Monad","Cont","Trans"],"ContT"]},{"tag":"TypeVar","contents":"r"}]},{"tag":"TypeVar","contents":"m"}]}],"edInstanceConstraints":[{"constraintClass":[["Control","Monad","Reader","Class"],"MonadAsk"],"constraintArgs":[{"tag":"TypeVar","contents":"r1"},{"tag":"TypeVar","contents":"m"}],"constraintData":null}]}},{"EDInstance":{"edInstanceClassName":[["Control","Monad","Reader","Class"],"MonadReader"],"edInstanceName":{"Ident":"monadReaderContT"},"edInstanceTypes":[{"tag":"TypeVar","contents":"r1"},{"tag":"TypeApp","contents":[{"tag":"TypeApp","contents":[{"tag":"TypeConstructor","contents":[["Control","Monad","Cont","Trans"],"ContT"]},{"tag":"TypeVar","contents":"r"}]},{"tag":"TypeVar","contents":"m"}]}],"edInstanceConstraints":[{"constraintClass":[["Control","Monad","Reader","Class"],"MonadReader"],"constraintArgs":[{"tag":"TypeVar","contents":"r1"},{"tag":"TypeVar","contents":"m"}],"constraintData":null}]}},{"EDInstance":{"edInstanceClassName":[["Control","Monad","State","Class"],"MonadState"],"edInstanceName":{"Ident":"monadStateContT"},"edInstanceTypes":[{"tag":"TypeVar","contents":"s"},{"tag":"TypeApp","contents":[{"tag":"TypeApp","contents":[{"tag":"TypeConstructor","contents":[["Control","Monad","Cont","Trans"],"ContT"]},{"tag":"TypeVar","contents":"r"}]},{"tag":"TypeVar","contents":"m"}]}],"edInstanceConstraints":[{"constraintClass":[["Control","Monad","State","Class"],"MonadState"],"constraintArgs":[{"tag":"TypeVar","contents":"s"},{"tag":"TypeVar","contents":"m"}],"constraintData":null}]}}],"efSourceSpan":{"start":[1,1],"name":"bower_components/purescript-transformers/src/Control/Monad/Cont/Trans.purs","end":[70,20]}}